{
	"mappings" : {
		"recipe" : {
			"properties" : {
				"step_by_step" : { "type" : "string", "analyzer" : "english"},
				"rating" : { "type" : "string"},
				"image_link" : { "type" : "string", "analyzer" : "keyword"},
				"count_rating" : { "type" : "integer" },
				"title" : { "type" : "string", "analyzer" : "english"},
				"url" : { "type" : "string", "analyzer" : "keyword"},
				"ingredients" : { "type" : "string", "analyzer" : "english"},
				"preparation_time" : { "type" : "integer"},
				"finish_time" : { "type" : "integer"}
			}
		}	

	}
}
